LICENSE
MANIFEST.in
README.md
requirements.txt
setup.py
discord/__init__.py
discord/__main__.py
discord/appinfo.py
discord/assets.py
discord/banner.txt
discord/channels.py
discord/client.py
discord/color.py
discord/colour.py
discord/embed.py
discord/enums.py
discord/file.py
discord/flags.py
discord/guild.py
discord/member.py
discord/message.py
discord/partial.py
discord/py.typed
discord/snowflake.py
discord/state.py
discord/ui.py
discord/user.py
discord/utils.py
discord/webhooks.py
discord.io.egg-info/PKG-INFO
discord.io.egg-info/SOURCES.txt
discord.io.egg-info/dependency_links.txt
discord.io.egg-info/requires.txt
discord.io.egg-info/top_level.txt
discord/api/__init__.py
discord/api/gateway.py
discord/api/rest.py
discord/bin/opus-x64.dll
discord/bin/opus-x86.dll
discord/components/__init__.py
discord/components/buttons.py
discord/components/modal.py
discord/components/select_menus.py
discord/events/__init__.py
discord/events/catalog.py
discord/events/channels.py
discord/events/core.py
discord/events/etc.py
discord/events/guilds.py
discord/events/interactions.py
discord/events/messages.py
discord/events/voice.py
discord/ext/cogs/__init__.py
discord/ext/commands/__init__.py
discord/ext/commands/bot.py
discord/ext/commands/context.py
discord/ext/commands/core.py
discord/http/__init__.py
discord/http/channels.py
discord/http/commands.py
discord/http/core.py
discord/http/guilds.py
discord/interactions/__init__.py
discord/interactions/commands.py
discord/interactions/interaction.py
discord/interactions/option_converter.py
discord/interactions/registry.py
discord/internal/__init__.py
discord/internal/dispatcher.py
discord/internal/exceptions.py
discord/internal/run_storage.py
discord/internal/warnings.py
discord/types/__init__.py
discord/types/allowed_mentions.py
discord/types/dict.py
discord/types/embed_parse.py
discord/voice/__init__.py
discord/voice/client.py
discord/voice/gateway.py
discord/voice/opus.py
discord/voice/players.py